MANIFEST.in
README.md
VERSION
setup.py
socotratools/__init__.py
socotratools/client.py
socotratools/dates.py
socotratools3.egg-info/PKG-INFO
socotratools3.egg-info/SOURCES.txt
socotratools3.egg-info/dependency_links.txt
socotratools3.egg-info/requires.txt
socotratools3.egg-info/top_level.txt