Metadata-Version: 1.2
Name: socotratools3
Version: 1.1.0
Summary: Socotra Tools for Python 3
Home-page: https://www.socotra.com
Maintainer: Victor Fateh
Maintainer-email: support@socotra.com
License: all rights reserved
Platform: UNKNOWN
